pyversity/__init__.py
pyversity/datatypes.py
pyversity/py.typed
pyversity/pyversity.py
pyversity/utils.py
pyversity/version.py
pyversity/strategies/__init__.py
pyversity/strategies/cover.py
pyversity/strategies/dpp.py
pyversity/strategies/mmr.py
pyversity/strategies/msd.py
pyversity/strategies/ssd.py
pyversity/strategies/utils.py
pyversity-0.1.1.dist-info/licenses/LICENSE
pyversity-0.1.1.dist-info/METADATA
pyversity-0.1.1.dist-info/WHEEL
pyversity-0.1.1.dist-info/top_level.txt
pyversity-0.1.1.dist-info/RECORD
