Metadata-Version: 2.4
Name: pyversity
Version: 0.1.1
Summary: Fast Diversification for Search & Retrieval
Author-email: Thomas van Dongen <thomas123@live.nl>
License: MIT License
Project-URL: Homepage, https://github.com/Pringled/pyversity
Project-URL: Bug Reports, https://github.com/Pringled/pyversity/issues
Project-URL: Source, https://github.com/Pringled/pyversity
Classifier: Development Status :: 4 - Beta
Classifier: Intended Audience :: Developers
Classifier: Intended Audience :: Science/Research
Classifier: Topic :: Scientific/Engineering :: Artificial Intelligence
Classifier: Topic :: Software Development :: Libraries
Classifier: License :: OSI Approved :: MIT License
Classifier: Programming Language :: Python :: 3 :: Only
Classifier: Programming Language :: Python :: 3.10
Classifier: Programming Language :: Python :: 3.11
Classifier: Programming Language :: Python :: 3.12
Classifier: Programming Language :: Python :: 3.13
Classifier: Natural Language :: English
Requires-Python: >=3.10
License-File: LICENSE
Requires-Dist: numpy
Provides-Extra: dev
Requires-Dist: ipython; extra == "dev"
Requires-Dist: mypy; extra == "dev"
Requires-Dist: pre-commit; extra == "dev"
Requires-Dist: pytest; extra == "dev"
Requires-Dist: pytest-coverage; extra == "dev"
Requires-Dist: ruff; extra == "dev"
Dynamic: license-file
